CMakeLists.txt
LICENSE
MANIFEST.in
README.md
setup.py
apps/CMakeLists.txt
apps/run_simulation.cpp
apps/python/LacZLacY.py
apps/python/brusselator.py
apps/python/decay.py
apps/python/sir.py
extern/CMakeLists.txt
extern/json/CMakeLists.txt
extern/json/cmake/ci.cmake
extern/json/cmake/config.cmake.in
extern/json/cmake/download_test_data.cmake
extern/json/cmake/nlohmann_jsonConfigVersion.cmake.in
extern/json/cmake/pkg-config.pc.in
extern/json/cmake/test.cmake
extern/json/docs/mkdocs/docs/integration/conan/CMakeLists.txt
extern/json/docs/mkdocs/docs/integration/vcpkg/CMakeLists.txt
extern/json/include/nlohmann/adl_serializer.hpp
extern/json/include/nlohmann/byte_container_with_subtype.hpp
extern/json/include/nlohmann/json.hpp
extern/json/include/nlohmann/json_fwd.hpp
extern/json/include/nlohmann/ordered_map.hpp
extern/json/include/nlohmann/detail/abi_macros.hpp
extern/json/include/nlohmann/detail/exceptions.hpp
extern/json/include/nlohmann/detail/hash.hpp
extern/json/include/nlohmann/detail/json_pointer.hpp
extern/json/include/nlohmann/detail/json_ref.hpp
extern/json/include/nlohmann/detail/macro_scope.hpp
extern/json/include/nlohmann/detail/macro_unscope.hpp
extern/json/include/nlohmann/detail/string_concat.hpp
extern/json/include/nlohmann/detail/string_escape.hpp
extern/json/include/nlohmann/detail/value_t.hpp
extern/json/include/nlohmann/detail/conversions/from_json.hpp
extern/json/include/nlohmann/detail/conversions/to_chars.hpp
extern/json/include/nlohmann/detail/conversions/to_json.hpp
extern/json/include/nlohmann/detail/input/binary_reader.hpp
extern/json/include/nlohmann/detail/input/input_adapters.hpp
extern/json/include/nlohmann/detail/input/json_sax.hpp
extern/json/include/nlohmann/detail/input/lexer.hpp
extern/json/include/nlohmann/detail/input/parser.hpp
extern/json/include/nlohmann/detail/input/position_t.hpp
extern/json/include/nlohmann/detail/iterators/internal_iterator.hpp
extern/json/include/nlohmann/detail/iterators/iter_impl.hpp
pystochsim.egg-info/PKG-INFO
pystochsim.egg-info/SOURCES.txt
pystochsim.egg-info/dependency_links.txt
pystochsim.egg-info/not-zip-safe
pystochsim.egg-info/top_level.txt
